{
  "allquestion": [
    
    {
      "dapan": "C",
      "link": "https://i.postimg.cc/q7GMH6px/11-1-C.png",
      "helpone": ["A","D"],
      "helptwo": ["https://i.postimg.cc/kgsVP3y2/hai-11-1-C-1.png", "https://i.postimg.cc/fbbVw2HB/hai-11-1-C-2.png"],
      "helpthree": ["B", "C", "C"],
      "giaithich": "bèo hoa dâu dễ sinh sôi nảy nở, hút khí cacbonic, sản sinh ra oxy. Trên vũ trụ lại có rất nhiều tia nhiễm xạ có tác động lên con người, lên sinh vật tạo nên sự đột biến sinh học, và mang bèo hoa dâu lên là để phục vụ mục đích nghiên cứu này"
    },
    {
      "dapan": "A",
      "link": "https://i.postimg.cc/rmbKf1Vz/11-2-A.png",
      "helpone": ["C","D"],
      "helptwo": ["https://i.postimg.cc/6Q1yTrgw/hai-11-2-A-12.png"],
      "helpthree": ["A", "A", "A"],
      "giaithich": "vườn quốc gia Núi Chúa là một vườn quốc gia tại huyện Ninh Hải, tỉnh Ninh Thuận, Việt Nam được thành lập vào năm 2003 theo Quyết định số 134/2003/QĐ-TTg của Thủ tướng Chính phủ Cộng hòa Xã hội Chủ nghĩa Việt Nam ngày 9 tháng 7 năm 2003. Năm 2021, đã được UNESCO công nhận là Khu dự trữ sinh quyển thế giới"
    }
    
  ]
}
